bracelet/__init__.py
bracelet/architecture.s.HTML
bracelet/module.MD
bracelet/module.s.HTML
bracelet/__agenda/maybes.s.HTML
bracelet/__agenda/priorities.s.HTML
bracelet/__agenda/processes/errout/script.py
bracelet/__agenda/processes/errout/start.py
bracelet/__agenda/processes/errout_v1/script.py
bracelet/__agenda/processes/errout_v1/start.py
bracelet/__agenda/processes/errout_v2/script.py
bracelet/__agenda/processes/errout_v2/start.py
bracelet/__license/license.s.HTML
bracelet/_book/advanced tutorial.s.HTML
bracelet/_book/book.s.HTML
bracelet/_book/example output.s.HTML
bracelet/_book/relevant.s.HTML
bracelet/_clique/__init__.py
bracelet/_clique/group/__init__.py
bracelet/_status/establish.py
bracelet/_status/status.proc.py
bracelet/_status/status.s.HTML
bracelet/_status/status_py.py
bracelet/_status/DB/records.json
bracelet/_status/monitors/-1_start/status_1.py
bracelet/_status/monitors/-1_start/chassis/modules/monitor_1.py
bracelet/_status/monitors/0_start/status_1.py
bracelet/_status/monitors/0_start/chassis/modules/monitor_1.py
bracelet/_status/monitors/1/status_1.py
bracelet/_status/monitors/1/stasis/path_1_health.py
bracelet/_status/monitors/1/stasis/path_2_health.py
bracelet/_status/monitors/2/status_1.py
bracelet/_status/monitors/2/stasis/1_health.py
bracelet/_status/monitors/2/stasis/2_health.py
bracelet/_status/monitors/2/stasis/modules/MODULE_1.py
bracelet/_status/monitors/3_empty_glob/status_1.py
bracelet/_status/monitors/4_bad_import/status_1.py
bracelet/_status/monitors/4_bad_import/stasis/1_health.py
bracelet/_status/monitors/5__file__/status_1.py
bracelet/_status/monitors/5__file__/stasis/1_health.py
bracelet/_status/monitors/5__file__/stasis/MODULES/MODULE_1.py
bracelet/_status/monitors/6_various/status_1.py
bracelet/_status/monitors/6_various/stasis/1_health.py
bracelet/_status/monitors/6_various/stasis/2_health.py
bracelet/_status/monitors/6_various/stasis/3_health.py
bracelet/_status/monitors/6_various/stasis/MODULES/MODULE_1.py
bracelet-1.0.2.dist-info/METADATA
bracelet-1.0.2.dist-info/WHEEL
bracelet-1.0.2.dist-info/entry_points.txt
bracelet-1.0.2.dist-info/top_level.txt
bracelet-1.0.2.dist-info/RECORD
